<trivia>
              <item category="six">
               <question>AC/DC guitarist Angus Young has used this guitar almost exclusively throughout his long career:</question>
	       <answers>
                  <answer>Gibson SG</answer>
                   <answer>Jackson Dinky</answer>
                   <answer>Fender Stratocaster</answer>
                   <answer>Ibanez Destroyer</answer>
	       </answers>
	</item>

               
               <item category="six">
                   <question>One of these songs DOES NOT FEATURE the guitar "talk box" effect:</question>
                    <answers>
                      <answer>Enter Sandman (Metallica)</answer>
                       <answer>Show Me the Way (Peter Frampton)</answer>
                       <answer>Sweet Emotion (Aerosmith)</answer>
                       <answer>Wake Up (Rage Against The Machine)</answer>
		    </answers>
		</item>


  <item category="six">
                   <question>In 1938 this guitarist was the first player ever to plug a non-lap steel guitar into an amp:</question>
                    <answers>
                      <answer>George Barnes</answer>
                       <answer>Carl Kress</answer>
                       <answer>Charlie Christian</answer>
                       <answer>Big Bill Broonzy</answer>
		    </answers>
		</item>


  <item category="six">
                   <question>Swedish shredder Yngwie Malmsteen is a long-time user of this guitar:</question>
                    <answers>
                      <answer>Fender Stratocaster</answer>
                       <answer>Home-made guitar his dad built with parts from a Volvo</answer>
                       <answer>Gibson Les Paul</answer>
                       <answer>Paul Reed Smith Special</answer>
		    </answers>
		</item>


<item category="six">
                   <question>The first pedal made by MXR Innovations in the early 1970s and used extensively by Edward Van Halen and many others:</question>
                    <answers>
                      <answer>Phase 90</answer>
                       <answer>Smooth Chorus</answer>
                       <answer>Overdrive Commander</answer>
                       <answer>Dynacomp</answer>
		    </answers>
		</item>

<item category="six">
                   <question>One of these songs DOES NOT FEATURE a guitar "Flanging" effect:</question>
		   <answers>
                     <answer>Purple Haze (Jimi Hendrix)</answer>
                      <answer>Killer Queen (Queen)</answer>
                      <answer>Barracuda (Heart)</answer>
                      <answer>Ain't Talkin' 'bout Love (Van Halen)</answer>
		   </answers>
		</item>

  <item category="six">
                   <question>Matt Pike (Sleep, High On Fire) is one of a few current metal guitarists who do this:</question>
                    <answers>
                      <answer>Play a 9-string guitar</answer>
                       <answer>Use battery-powered amplifiers</answer>
                       <answer>100 push-ups before a gig</answer>
                       <answer>Make their own plectrums out of hemp</answer>
		    </answers>
		</item>

<item category="six">
                 <question>ALL major differences between a stock Fender Stratocaster and a stock Gibson Les Paul EXCEPT:</question>
		  <answers>
                     <answer>Number of pick-up selector switches</answer>
                     <answer>Number of pick-ups</answer>
                     <answer>Number of frets</answer>
                     <answer>Number of control knobs</answer>
                 </answers>
	</item>

<item category="six">
 <question>Kinks guitarist Ray Davies was able to get a very distorted guitar sound on early Kinks recordings because he:</question>
                     <answers>
                       <answer>Slit his amp's speaker cone with a razor</answer>
                        <answer>Tuned his guitar down an octave</answer>
                        <answer>Used special tubes he acquired from the BBC</answer>
                        <answer>Let Jeff Beck play all of his parts</answer>
		      </answers>
              </item>



<item category="six">
                 <question>Originally called Electric Sound Products, this company is now one of the most popular guitar makers in the world, especially among metal players:</question>
		  <answers>
                     <answer>ESP</answer>
                     <answer>Dean</answer>
                     <answer>Jackson</answer>
                     <answer>Schnecter</answer>
                 </answers>
	</item>


 <item category="six">
                   <question>A Device placed on a stringed instrument that raises and lowers the pitch and allows for basic chords to be played all over the neck:</question>
                    <answers>
                      <answer>A Capo</answer>
                       <answer>A Whammy Bar</answer>
                       <answer>A String Bender</answer>
                       <answer>A String Thingy</answer>
		    </answers>
		</item>

	        
		<item category="six">
                 <question>"The Whizzer" is:</question>
		  <answers>
                     <answer>A device that changes the settings on Neil Young's amp</answer>
                     <answer>James Hettfield's nickname</answer>
                     <answer>A guitar pedal used by axeman Uli Jon Roth</answer>
                     <answer>Guitarist slang for a really long guitar strap</answer>
                 </answers>
	</item>

	 <item category="six">
                   <question>This British equipment company's well-known amplifier model was used by The Beatles and still used by Tom Petty, Brian May, and many others: </question>
                    <answers>
                      <answer>Vox AC-30</answer>
                       <answer>Ampeg SVT</answer>
                       <answer>Kay Western Auto</answer>
                       <answer>Fender Twin</answer>
		    </answers>
		</item>

	<item category="six">
                  <question>A single-pickup guitar produced by Fender in the 1950s and played by Luther Perkins, Syd Barrett, and Joe Strummer:</question>
 		  <answers>
                    <answer>Fender Esquire</answer>
                    <answer>Fender Broadcaster</answer>
                    <answer>Fender Jazzmaster</answer>
                    <answer>Fender Jaguar</answer>
		  </answers>
	</item>



	<item category="six">
                  <question>Not only did he help create the Les Paul solid body guitar, Les Paul also invented this:</question>
 		  <answers>
                    <answer>Multi-tracking</answer>
                    <answer>The toaster</answer>
                    <answer>Dolby</answer>
                    <answer>Reverb</answer>
		  </answers>
	</item>


<item category="six">
                 <question>Stevie Ray Vaughan used this to bind the callouses on the fingers of his fretting hand:</question>
		 <answers>
                    <answer>Superglue</answer>
                    <answer>Band Aids</answer>
                    <answer>Duct tape</answer>
                    <answer>Saliva</answer>
		 </answers>
	</item>

<item category="six">
                   <question>The name of Brian May's very famous home-made guitar, built with the aid of his father back in the early 1960s:</question>
		   <answers>
                     <answer>The Red Special</answer>
                      <answer>Rosebud</answer>
                      <answer>Swordfish</answer>
                      <answer>Cherry Bomb</answer>
		   </answers>
		</item>


	<item category="six">
               <question>Famous "drug" bottle used for Slide/Bottleneck guitar by Duane Allman and later picked up by others, including Derek Trucks and Rory Gallagher:</question>
	       <answers>
                  <answer>Coricidin</answer>
                   <answer>Vicks</answer>
                   <answer>Sudafed</answer>
                   <answer>Nyquil</answer>
	       </answers>
	</item>

	
	
	<item category="six">
                   <question>Chicago guitar player Terry Kath helped found a company that launched this legendary amplifier that was named after a farm animal's body part:</question>
		   <answers>
                     <answer>Pignose</answer>
                      <answer>Cowbutt</answer>
                      <answer>Horsetail</answer>
                      <answer>ChickenScratch</answer>
		   </answers>
		</item>


<item category="six">
                 <question>This rotating speaker system was originally used with the Hammond organ, but it has appeared on many guitar recordings, including Jimi Hendrix's "Little Wing":</question>
		 <answers>
                    <answer>The Leslie Speaker</answer>
                    <answer>"The Slapback"</answer>
                    <answer>The Piezoelectric Speaker</answer>
                    <answer>The "Hi-Fidelity"</answer>
		 </answers>
	</item>



	<item category="six">
               <question>This is created by compressing the peaks of an instrument's sound wave and adding overtones:</question>
	       <answers>
                  <answer>Distortion</answer>
                   <answer>A chorus effect</answer>
                   <answer>Pitch Shifting</answer>
                   <answer>Harmonics</answer>
	       </answers>
	</item>


	 <item category="six">
                    <question>Legendary guitarist Jimmy Page was also a darn fine producer and pioneered the use of this effect which can be heard on "Whole Lotta Love":</question>
		    <answers>
                      <answer>Backwards Echo</answer>
                       <answer>Dolby</answer>
                       <answer>Guitar Overdubbing</answer>
                       <answer>Phasing</answer>
		     </answers>
		</item>



 <item category="six">
                    <question>All of these bands have players who have made extensive use of 7-string guitars EXCEPT:</question>
		    <answers>
                      <answer>Wilco</answer>
                       <answer>Dream Theater</answer>
                       <answer>Limp Bizkit</answer>
                       <answer>Deftones</answer>
		     </answers>
		</item>

</trivia>
